pypda/__init__.py
pypda/cli.py
pypda/hmm.py
pypda/parameters.py
pypda/pulse_model.py
pypda/pulse_wave.py
pypda/api/__init__.py
pypda/api/plot.py
pypda/api/sample_test.py
pypda/wavelets/__init__.py
pypda/wavelets/triang_gaussian.py
pypda/wavelets/waveform.py
pypda-0.4.2.dist-info/AUTHORS.rst
pypda-0.4.2.dist-info/LICENSE
pypda-0.4.2.dist-info/METADATA
pypda-0.4.2.dist-info/WHEEL
pypda-0.4.2.dist-info/entry_points.txt
pypda-0.4.2.dist-info/top_level.txt
pypda-0.4.2.dist-info/RECORD
