Metadata-Version: 2.1
Name: pypda
Version: 0.4.2
Summary: A Pythonic toolkit to generate synthetic blood pressure waveforms based on principle of pulse decomposition analysis (PDA).
Home-page: https://github.com/taoyilee/pypda
Author: Tao-Yi Lee
Author-email: taoyil@uci.edu
License: MIT license
Keywords: pypda
Platform: UNKNOWN
Classifier: Development Status :: 2 - Pre-Alpha
Classifier: Intended Audience :: Developers
Classifier: License :: OSI Approved :: MIT License
Classifier: Natural Language :: English
Classifier: Programming Language :: Python :: 3
Classifier: Programming Language :: Python :: 3.5
Classifier: Programming Language :: Python :: 3.6
Classifier: Programming Language :: Python :: 3.7
Classifier: Programming Language :: Python :: 3.8
Requires-Python: >=3.5
Requires-Dist: Click (>=7.0)
Requires-Dist: matplotlib (==3.1.3)
Requires-Dist: numpy (==1.18.1)
Requires-Dist: scipy (==1.4.1)
Requires-Dist: scikit-learn (==0.22.1)
